gridding_fast.so
aartfaac_arthur-0.5.data/scripts/arthur-plot.py
aartfaac_arthur-0.5.data/scripts/arthur-stream.py
aartfaac_arthur-0.5.dist-info/DESCRIPTION.rst
aartfaac_arthur-0.5.dist-info/METADATA
aartfaac_arthur-0.5.dist-info/RECORD
aartfaac_arthur-0.5.dist-info/WHEEL
aartfaac_arthur-0.5.dist-info/metadata.json
aartfaac_arthur-0.5.dist-info/top_level.txt
arthur/__init__.py
arthur/constants.py
arthur/data.py
arthur/gridding.py
arthur/imaging.py
arthur/io.py
arthur/lba_outer.dat
arthur/main.py
arthur/plot.py
arthur/stream.py
arthur/writer.py
