Metadata-Version: 2.0
Name: aartfaac-arthur
Version: 0.5
Summary: AARTFAAC visualisation utilities
Home-page: https://github.com/transientskp/aartfaac-arthur
Author: Gijs Molenaar
Author-email: gijs@pythonic.nl
License: GPL3
Keywords: science astronomy aartfaac
Platform: UNKNOWN
Classifier: Development Status :: 4 - Beta
Classifier: Intended Audience :: Science/Research
Classifier: License :: OSI Approved :: GNU General Public License v3 (GPLv3)
Classifier: Operating System :: POSIX
Classifier: Programming Language :: Python :: 3.5
Classifier: Topic :: Scientific/Engineering
Requires-Dist: astropy
Requires-Dist: backports.functools-lru-cache
Requires-Dist: ephem
Requires-Dist: matplotlib
Requires-Dist: monotonic
Requires-Dist: pillow
Requires-Dist: python-casacore
Requires-Dist: scipy
Requires-Dist: six
